Workbook

Sheet Marketing Campaign Performance 
A1: Marketing Campaign Performance Dashboard
A3: Row Labels | B3: Sum of Impressions | C3: Sum of Clicks | D3: Sum of Leads | E3: Sum of Applications | F3: Sum of Enrollments | J3: CTR (%) | K3: Click-to-Lead (%) | L3: Lead-to-Application (%) | M3: Application-to-Enrollment (%) | N3: ROI (%) | O3: ROAS | P3: Planned Budget (₹) | Q3: Actual Cost (₹) | R3: Cost vs Budget (%)
A4: Facebook | B4: 31329302 | C4: 1740443 | D4: 350452 | E4: 191054 | F4: 94199 | J4: =C4/B4*100 -> 5.5553201 | K4: =D4/C4*100 -> 20.135793 | L4: =E4/D4*100 -> 54.516453 | M4: =F4/E4*100 -> 49.304909 | N4: =IFERROR((SUMIF(CampaignPerformance!$D$2:$D$1000,$A4,CampaignPerformance!$L$2:$L$1000)-Q4)/Q4*100,0) -> 2245.7814 | O4: =IFERROR(SUMIF(CampaignPerformance!$D$2:$D$1000,$A4,CampaignPerformance!$L$2:$L$1000)/Q4,0) -> 23.457814 | P4: =SUMIF(CampaignMeta!I:I,A4,CampaignMeta!E:E) -> 1500000 | Q4: =SUMIF(CampaignPerformance!$D$2:$D$1000,$A4,CampaignPerformance!$K$2:$K$1000) -> 22051324 | R4: =IFERROR((Q4-P4)/P4*100,0) -> 1370.0883
A5: Google Ads | B5: 31963554 | C5: 1751859 | D5: 346441 | E5: 190327 | F5: 95402 | J5: =C5/B5*100 -> 5.4808017 | K5: =D5/C5*100 -> 19.775621 | L5: =E5/D5*100 -> 54.937782 | M5: =F5/E5*100 -> 50.125311 | N5: =IFERROR((SUMIF(CampaignPerformance!$D$2:$D$1000,$A5,CampaignPerformance!$L$2:$L$1000)-Q5)/Q5*100,0) -> 2197.1405 | O5: =IFERROR(SUMIF(CampaignPerformance!$D$2:$D$1000,$A5,CampaignPerformance!$L$2:$L$1000)/Q5,0) -> 22.971405 | P5: =SUMIF(CampaignMeta!I:I,A5,CampaignMeta!E:E) -> 1800000 | Q5: =SUMIF(CampaignPerformance!$D$2:$D$1000,$A5,CampaignPerformance!$K$2:$K$1000) -> 23158076 | R5: =IFERROR((Q5-P5)/P5*100,0) -> 1186.5598
A6: Instagram | B6: 24699279 | C6: 1347998 | D6: 270522 | E6: 148302 | F6: 75249 | J6: =C6/B6*100 -> 5.4576411 | K6: =D6/C6*100 -> 20.068427 | L6: =E6/D6*100 -> 54.82068 | M6: =F6/E6*100 -> 50.740381 | N6: =IFERROR((SUMIF(CampaignPerformance!$D$2:$D$1000,$A6,CampaignPerformance!$L$2:$L$1000)-Q6)/Q6*100,0) -> 2300.7736 | O6: =IFERROR(SUMIF(CampaignPerformance!$D$2:$D$1000,$A6,CampaignPerformance!$L$2:$L$1000)/Q6,0) -> 24.007736 | P6: =SUMIF(CampaignMeta!I:I,A6,CampaignMeta!E:E) -> 1200000 | Q6: =SUMIF(CampaignPerformance!$D$2:$D$1000,$A6,CampaignPerformance!$K$2:$K$1000) -> 17285042 | R6: =IFERROR((Q6-P6)/P6*100,0) -> 1340.4202
A7: LinkedIn | B7: 26146791 | C7: 1460099 | D7: 292161 | E7: 163739 | F7: 83522 | J7: =C7/B7*100 -> 5.5842379 | K7: =D7/C7*100 -> 20.009671 | L7: =E7/D7*100 -> 56.044099 | M7: =F7/E7*100 -> 51.009228 | N7: =IFERROR((SUMIF(CampaignPerformance!$D$2:$D$1000,$A7,CampaignPerformance!$L$2:$L$1000)-Q7)/Q7*100,0) -> 2444.5564 | O7: =IFERROR(SUMIF(CampaignPerformance!$D$2:$D$1000,$A7,CampaignPerformance!$L$2:$L$1000)/Q7,0) -> 25.445564 | P7: =SUMIF(CampaignMeta!I:I,A7,CampaignMeta!E:E) -> 1000000 | Q7: =SUMIF(CampaignPerformance!$D$2:$D$1000,$A7,CampaignPerformance!$K$2:$K$1000) -> 18258975 | R7: =IFERROR((Q7-P7)/P7*100,0) -> 1725.8975
A8: YouTube | B8: 15019263 | C8: 838013 | D8: 161708 | E8: 90194 | F8: 43942 | J8: =C8/B8*100 -> 5.579588 | K8: =D8/C8*100 -> 19.296598 | L8: =E8/D8*100 -> 55.775843 | M8: =F8/E8*100 -> 48.719427 | N8: =IFERROR((SUMIF(CampaignPerformance!$D$2:$D$1000,$A8,CampaignPerformance!$L$2:$L$1000)-Q8)/Q8*100,0) -> 2112.5746 | O8: =IFERROR(SUMIF(CampaignPerformance!$D$2:$D$1000,$A8,CampaignPerformance!$L$2:$L$1000)/Q8,0) -> 22.125746 | P8: =SUMIF(CampaignMeta!I:I,A8,CampaignMeta!E:E) -> 800000 | Q8: =SUMIF(CampaignPerformance!$D$2:$D$1000,$A8,CampaignPerformance!$K$2:$K$1000) -> 10694714 | R8: =IFERROR((Q8-P8)/P8*100,0) -> 1236.8392
A9: Grand Total | B9: 129158189 | C9: 7138412 | D9: 1421284 | E9: 783616 | F9: 392314 | N9: =IFERROR((SUM(CampaignPerformance!L2:L764)-Q9)/Q9*100,0) -> 2267.9681 | O9: =IFERROR(SUM(CampaignPerformance!L2:L764)/Q9,0) -> 23.679681 | P9: =SUM(P4:P8) -> 6300000 | Q9: =SUM(Q4:Q8) -> 91448131 | R9: =IFERROR((Q9-P9)/P9*100,0) -> 1351.5576

Sheet Business Insights Report
A1: Business Insights Report: Marketing Campaign Performance
A3: Objective
A4: The objective of this analysis is to evaluate marketing campaign performance across Facebook, Google Ads, Instagram, LinkedIn, and YouTube by examining audience engagement, conversion rates, enrollments, costs, and return on investment (ROI).
A6: Key Findings
A7: The analysis compares five marketing platforms using impressions, clicks, leads, applications, enrollments, campaign costs, revenue, and ROI to identify differences in performance.
A9: Platform Performance
A10: LinkedIn recorded the highest ROI at 2,444.56%, followed by Instagram at 2,300.77%, Facebook at 2,245.78%, Google Ads at 2,197.14%, and YouTube at 2,112.57%.
A12: Budget and Cost Analysis
A13: The total planned budget was ₹63,00,000, while total actual campaign costs were approximately ₹9,14,48,131. Actual spending substantially exceeded the planned budget, indicating a need for closer budget monitoring, cost control, and investigation of the differences between planned and actual costs.
A15: Recommendations
A16: The business should investigate why actual campaign costs exceed the planned budget. LinkedIn showed the highest reported ROI, making it a platform worth investigating for further investment, while YouTube's comparatively lower ROI should be reviewed for optimization opportunities. Before reallocating budgets, validate the cost and revenue calculations, compare conversion rates across platforms, and monitor campaign performance regularly to ensure that future spending aligns with business objectives.

Sheet Roi_Analysis
A1: Platform | B1: ROI (%)
A2: Facebook | B2: ='Marketing Campaign Performance '!N4 -> 2245.7814
A3: Google Ads | B3: ='Marketing Campaign Performance '!N5 -> 2197.1405
A4: Instagram | B4: ='Marketing Campaign Performance '!N6 -> 2300.7736
A5: LinkedIn | B5: ='Marketing Campaign Performance '!N7 -> 2444.5564
A6: YouTube | B6: ='Marketing Campaign Performance '!N8 -> 2112.5746

Sheet CampaignPerformance
A1: Date | B1: CampaignID | C1: CampaignName | D1: Platform | E1: TargetAudience | F1: Impressions | G1: Clicks | H1: Leads | I1: Applications | J1: Enrollments | K1: Cost (₹) | L1: Revenue (₹) | M1: Region | N1: Duplicate_Check | O1: Funnel_Check | P1: CTR (%) | Q1: Click_to_Lead_Rate (%) | R1: Lead_to_Application_Rate (%) | S1: Application_to_Enrollment_Rate (%) | T1: ROI (%) | U1: ROAS
A2: 45292 | B2: AD004 | C2: Hackathon | D2: YouTube | E2: 17–21 Age | F2: 285708 | G2: 16956 | H2: 4087 | I2: 2547 | J2: 1148 | K2: 275457.87 | L2: 4615838 | M2: West India | N2: =COUNTIFS(A:A,A2,B:B,B2,C:C,C2,D:D,D2,E:E,E2,F:F,F2,G:G,G2,H:H,H2,I:I,I2,J:J,J2,K:K,K2,L:L,L2,M:M,M2) -> 1 | O2: =IF(AND(G2<=F2,H2<=G2,I2<=H2,J2<=I2),"OK","Check") -> OK | P2: =IFERROR(G2/F2*100,0) -> 5.9347306 | Q2: =IFERROR(H2/G2*100,0) -> 24.103562 | R2: =IFERROR(I2/H2*100,0) -> 62.31955 | S2: =IFERROR(J2/I2*100,0) -> 45.072634 | T2: =IFERROR((L2-K2)/K2*100,0) -> 1575.6966 | U2: =IFERROR(L2/K2,0) -> 16.756966
A3: 45293 | B3: AD004 | C3: Hackathon | D3: YouTube | E3: 17–21 Age | F3: 140449 | G3: 10082 | H3: 1815 | I3: 951 | J3: 565 | K3: 133025.86 | L3: 3513169.9 | M3: North India | N3: =COUNTIFS(A:A,A3,B:B,B3,C:C,C3,D:D,D3,E:E,E3,F:F,F3,G:G,G3,H:H,H3,I:I,I3,J:J,J3,K:K,K3,L:L,L3,M:M,M3) -> 1 | O3: =IF(AND(G3<=F3,H3<=G3,I3<=H3,J3<=I3),"OK","Check") -> OK | P3: =IFERROR(G3/F3*100,0) -> 7.1784064 | Q3: =IFERROR(H3/G3*100,0) -> 18.00238 | R3: =IFERROR(I3/H3*100,0) -> 52.396694 | S3: =IFERROR(J3/I3*100,0) -> 59.411146 | T3: =IFERROR((L3-K3)/K3*100,0) -> 2540.9676 | U3: =IFERROR(L3/K3,0) -> 26.409676
A4: 45294 | B4: AD004 | C4: Hackathon | D4: YouTube | E4: 17–21 Age | F4: 140958 | G4: 7474 | H4: 1169 | I4: 683 | J4: 343 | K4: 135765.61 | L4: 1051924.9 | M4: North India | N4: =COUNTIFS(A:A,A4,B:B,B4,C:C,C4,D:D,D4,E:E,E4,F:F,F4,G:G,G4,H:H,H4,I:I,I4,J:J,J4,K:K,K4,L:L,L4,M:M,M4) -> 1 | O4: =IF(AND(G4<=F4,H4<=G4,I4<=H4,J4<=I4),"OK","Check") -> OK | P4: =IFERROR(G4/F4*100,0) -> 5.3022886 | Q4: =IFERROR(H4/G4*100,0) -> 15.640888 | R4: =IFERROR(I4/H4*100,0) -> 58.426005 | S4: =IFERROR(J4/I4*100,0) -> 50.219619 | T4: =IFERROR((L4-K4)/K4*100,0) -> 674.80953 | U4: =IFERROR(L4/K4,0) -> 7.7480953
A5: 45295 | B5: AD004 | C5: Hackathon | D5: YouTube | E5: 22–27 Age | F5: 257823 | G5: 16841 | H5: 3179 | I5: 1584 | J5: 698 | K5: 229715.44 | L5: 3850639.6 | M5: West India | N5: =COUNTIFS(A:A,A5,B:B,B5,C:C,C5,D:D,D5,E:E,E5,F:F,F5,G:G,G5,H:H,H5,I:I,I5,J:J,J5,K:K,K5,L:L,L5,M:M,M5) -> 1 | O5: =IF(AND(G5<=F5,H5<=G5,I5<=H5,J5<=I5),"OK","Check") -> OK | P5: =IFERROR(G5/F5*100,0) -> 6.5320006 | Q5: =IFERROR(H5/G5*100,0) -> 18.876551 | R5: =IFERROR(I5/H5*100,0) -> 49.82699 | S5: =IFERROR(J5/I5*100,0) -> 44.065657 | T5: =IFERROR((L5-K5)/K5*100,0) -> 1576.265 | U5: =IFERROR(L5/K5,0) -> 16.76265
A6: 45296 | B6: AD004 | C6: Hackathon | D6: YouTube | E6: 25–35 Age | F6: 98595 | G6: 7293 | H6: 1340 | I6: 854 | J6: 368 | K6: 52360.96 | L6: 1543262.9 | M6: West India | N6: =COUNTIFS(A:A,A6,B:B,B6,C:C,C6,D:D,D6,E:E,E6,F:F,F6,G:G,G6,H:H,H6,I:I,I6,J:J,J6,K:K,K6,L:L,L6,M:M,M6) -> 1 | O6: =IF(AND(G6<=F6,H6<=G6,I6<=H6,J6<=I6),"OK","Check") -> OK | P6: =IFERROR(G6/F6*100,0) -> 7.3969268 | Q6: =IFERROR(H6/G6*100,0) -> 18.373783 | R6: =IFERROR(I6/H6*100,0) -> 63.731343 | S6: =IFERROR(J6/I6*100,0) -> 43.091335 | T6: =IFERROR((L6-K6)/K6*100,0) -> 2847.354 | U6: =IFERROR(L6/K6,0) -> 29.47354
A7: 45297 | B7: AD004 | C7: Hackathon | D7: YouTube | E7: 22–27 Age | F7: 68114 | G7: 5377 | H7: 909 | I7: 505 | J7: 222 | K7: 27454.35 | L7: 1717163.9 | M7: North India | N7: =COUNTIFS(A:A,A7,B:B,B7,C:C,C7,D:D,D7,E:E,E7,F:F,F7,G:G,G7,H:H,H7,I:I,I7,J:J,J7,K:K,K7,L:L,L7,M:M,M7) -> 1 | O7: =IF(AND(G7<=F7,H7<=G7,I7<=H7,J7<=I7),"OK","Check") -> OK | P7: =IFERROR(G7/F7*100,0) -> 7.8941187 | Q7: =IFERROR(H7/G7*100,0) -> 16.905338 | R7: =IFERROR(I7/H7*100,0) -> 55.555556 | S7: =IFERROR(J7/I7*100,0) -> 43.960396 | T7: =IFERROR((L7-K7)/K7*100,0) -> 6154.6151 | U7: =IFERROR(L7/K7,0) -> 62.546151
A8: 45298 | B8: AD004 | C8: Hackathon | D8: YouTube | E8: 17–21 Age | F8: 175572 | G8: 6855 | H8: 1452 | I8: 757 | J8: 346 | K8: 95497.97 | L8: 2598807.5 | M8: East India | N8: =COUNTIFS(A:A,A8,B:B,B8,C:C,C8,D:D,D8,E:E,E8,F:F,F8,G:G,G8,H:H,H8,I:I,I8,J:J,J8,K:K,K8,L:L,L8,M:M,M8) -> 1 | O8: =IF(AND(G8<=F8,H8<=G8,I8<=H8,J8<=I8),"OK","Check") -> OK | P8: =IFERROR(G8/F8*100,0) -> 3.9043811 | Q8: =IFERROR(H8/G8*100,0) -> 21.181619 | R8: =IFERROR(I8/H8*100,0) -> 52.134986 | S8: =IFERROR(J8/I8*100,0) -> 45.706737 | T8: =IFERROR((L8-K8)/K8*100,0) -> 2621.3223 | U8: =IFERROR(L8/K8,0) -> 27.213223
A9: 45299 | B9: AD004 | C9: Hackathon | D9: YouTube | E9: 22–27 Age | F9: 231966 | G9: 9373 | H9: 1934 | I9: 1247 | J9: 553 | K9: 175649 | L9: 2558956.4 | M9: West India | N9: =COUNTIFS(A:A,A9,B:B,B9,C:C,C9,D:D,D9,E:E,E9,F:F,F9,G:G,G9,H:H,H9,I:I,I9,J:J,J9,K:K,K9,L:L,L9,M:M,M9) -> 1 | O9: =IF(AND(G9<=F9,H9<=G9,I9<=H9,J9<=I9),"OK","Check") -> OK | P9: =IFERROR(G9/F9*100,0) -> 4.0406784 | Q9: =IFERROR(H9/G9*100,0) -> 20.633735 | R9: =IFERROR(I9/H9*100,0) -> 64.477766 | S9: =IFERROR(J9/I9*100,0) -> 44.346431 | T9: =IFERROR((L9-K9)/K9*100,0) -> 1356.8579 | U9: =IFERROR(L9/K9,0) -> 14.568579
A10: 45300 | B10: AD004 | C10: Hackathon | D10: YouTube | E10: 17–21 Age | F10: 281339 | G10: 12310 | H10: 2329 | I10: 1319 | J10: 734 | K10: 126723.85 | L10: 4265725 | M10: West India | N10: =COUNTIFS(A:A,A10,B:B,B10,C:C,C10,D:D,D10,E:E,E10,F:F,F10,G:G,G10,H:H,H10,I:I,I10,J:J,J10,K:K,K10,L:L,L10,M:M,M10) -> 1 | O10: =IF(AND(G10<=F10,H10<=G10,I10<=H10,J10<=I10),"OK","Check") -> OK | P10: =IFERROR(G10/F10*100,0) -> 4.3755043 | Q10: =IFERROR(H10/G10*100,0) -> 18.919578 | R10: =IFERROR(I10/H10*100,0) -> 56.633748 | S10: =IFERROR(J10/I10*100,0) -> 55.648218 | T10: =IFERROR((L10-K10)/K10*100,0) -> 3266.158 | U10: =IFERROR(L10/K10,0) -> 33.66158
A11: 45301 | B11: AD004 | C11: Hackathon | D11: YouTube | E11: 22–27 Age | F11: 98805 | G11: 6952 | H11: 1479 | I11: 955 | J11: 455 | K11: 49446.12 | L11: 3012430 | M11: North India | N11: =COUNTIFS(A:A,A11,B:B,B11,C:C,C11,D:D,D11,E:E,E11,F:F,F11,G:G,G11,H:H,H11,I:I,I11,J:J,J11,K:K,K11,L:L,L11,M:M,M11) -> 1 | O11: =IF(AND(G11<=F11,H11<=G11,I11<=H11,J11<=I11),"OK","Check") -> OK | P11: =IFERROR(G11/F11*100,0) -> 7.0360812 | Q11: =IFERROR(H11/G11*100,0) -> 21.274453 | R11: =IFERROR(I11/H11*100,0) -> 64.570656 | S11: =IFERROR(J11/I11*100,0) -> 47.643979 | T11: =IFERROR((L11-K11)/K11*100,0) -> 5992.3487 | U11: =IFERROR(L11/K11,0) -> 60.923487
A12: 45302 | B12: AD004 | C12: Hackathon | D12: YouTube | E12: 25–35 Age | F12: 144093 | G12: 11451 | H12: 1776 | I12: 934 | J12: 480 | K12: 104177.45 | L12: 1723113.8 | M12: North India | N12: =COUNTIFS(A:A,A12,B:B,B12,C:C,C12,D:D,D12,E:E,E12,F:F,F12,G:G,G12,H:H,H12,I:I,I12,J:J,J12,K:K,K12,L:L,L12,M:M,M12) -> 1 | O12: =IF(AND(G12<=F12,H12<=G12,I12<=H12,J12<=I12),"OK","Check") -> OK | P12: =IFERROR(G12/F12*100,0) -> 7.9469509 | Q12: =IFERROR(H12/G12*100,0) -> 15.509562 | R12: =IFERROR(I12/H12*100,0) -> 52.59009 | S12: =IFERROR(J12/I12*100,0) -> 51.391863 | T12: =IFERROR((L12-K12)/K12*100,0) -> 1554.0181 | U12: =IFERROR(L12/K12,0) -> 16.540181
A13: 45303 | B13: AD004 | C13: Hackathon | D13: YouTube | E13: 25–35 Age | F13: 158894 | G13: 6588 | H13: 1470 | I13: 867 | J13: 405 | K13: 102314.09 | L13: 3080880.5 | M13: Pan India | N13: =COUNTIFS(A:A,A13,B:B,B13,C:C,C13,D:D,D13,E:E,E13,F:F,F13,G:G,G13,H:H,H13,I:I,I13,J:J,J13,K:K,K13,L:L,L13,M:M,M13) -> 1 | O13: =IF(AND(G13<=F13,H13<=G13,I13<=H13,J13<=I13),"OK","Check") -> OK | P13: =IFERROR(G13/F13*100,0) -> 4.1461603 | Q13: =IFERROR(H13/G13*100,0) -> 22.313297 | R13: =IFERROR(I13/H13*100,0) -> 58.979592 | S13: =IFERROR(J13/I13*100,0) -> 46.712803 | T13: =IFERROR((L13-K13)/K13*100,0) -> 2911.1986 | U13: =IFERROR(L13/K13,0) -> 30.111986
... A764: 45961 | B764: AD002 | C764: MBA Admission | D764: Facebook | E764: 21–35 Age | F764: 267804 | G764: 19472 | H764: 4863 | I764: 2431 | J764: 1100 | K764: 251059.32 | L764: 6675311.7 | M764: Pan India | N764: =COUNTIFS(A:A,A764,B:B,B764,C:C,C764,D:D,D764,E:E,E764,F:F,F764,G:G,G764,H:H,H764,I:I,I764,J:J,J764,K:K,K764,L:L,L764,M:M,M764) -> 1 | O764: =IF(AND(G764<=F764,H764<=G764,I764<=H764,J764<=I764),"OK","Check") -> OK | P764: =IFERROR(G764/F764*100,0) -> 7.2709892 | Q764: =IFERROR(H764/G764*100,0) -> 24.974322 | R764: =IFERROR(I764/H764*100,0) -> 49.989718 | S764: =IFERROR(J764/I764*100,0) -> 45.248869 | T764: =IFERROR((L764-K764)/K764*100,0) -> 2558.8583 | U764: =IFERROR(L764/K764,0) -> 26.588583
K766: =SUM(K2:K764) -> 91448131 | L766: =SUM(L2:L764) -> 2.1654626e+09
L767: =(L766-K766)/K766*100 -> 2267.9681
L768: =L766/K766 -> 23.679681

Sheet CampaignMeta
A1: CampaignID | B1: Objective | C1: StartDate | D1: EndDate | E1: Budget (₹) | F1: Campaign Type | G1: Creative Type | H1: Manager | I1: Channel | J1: Conversion Goal
A2: AD001 | B2: Lead Generation | C2: 2024-03-01 | D2: 2024-08-31 | E2: 1800000 | F2: Paid Search | G2: Static Ads | H2: Priya | I2: Google Ads | J2: Application
A3: AD002 | B3: Admissions | C3: 2025-05-01 | D3: 2025-10-31 | E3: 1500000 | F3: Paid Social | G3: Video | H3: Rohit | I3: Facebook | J3: Lead
A4: AD003 | B4: Career Promotion | C4: 2025-01-01 | D4: 2025-05-31 | E4: 1000000 | F4: Professional Networking | G4: Carousel | H4: Ananya | I4: LinkedIn | J4: Placement
A5: AD004 | B5: Brand Awareness | C5: 2024-01-01 | D5: 2024-03-31 | E5: 800000 | F5: Event Marketing | G5: Video | H5: Arjun | I5: YouTube | J5: Registration
A6: AD005 | B6: Student Exchange | C6: 2024-08-01 | D6: 2024-12-31 | E6: 1200000 | F6: Social Media | G6: Reels | H6: Megha | I6: Instagram | J6: Application

Sheet ChannelRates
A1: Channel | B1: AvgCPM | C1: AvgCPC | D1: Remarks
A2: Google Ads | B2: 80 | C2: 12 | D2: High search volume
A3: Facebook | B3: 70 | C3: 10 | D3: Engagement focused
A4: LinkedIn | B4: 120 | C4: 20 | D4: Professional targeting
A5: YouTube | B5: 90 | C5: 15 | D5: Video rich
A6: Instagram | B6: 60 | C6: 9 | D6: Youth appeal
